{
  "@context": {
  "@vocab": "http://schema.org/",
  "ccss": "http://www.corestandards.org/",
  "dct": "http://purl.org/dc/terms/",
  "dcmitype": "http://purl.org/dc/dcmitype/",
  "edm": "http://www.europeana.eu/schemas/edm",
  "ore": "http://www.openarchives.org/ore/terms/",
  "text": {
    "@id": "http://schema.org/text",
    "@type": "http://ns.ontowiki.net/SysOnt/Markdown"
  },
  "name": {
    "@id": "http://schema.org/text",
    "@type": "http://ns.ontowiki.net/SysOnt/Markdown"
  }
}
,
  "@id": "https://dp.la/primary-source-sets/sets/the-adventures-of-huckleberry-finn-by-mark-twain",
  "@type": "CreativeWork",
  "dct:type": "dcmitype:InteractiveResource",
  "name": "*The Adventures of Huckleberry Finn* by Mark Twain",
    "thumbnailUrl": "https://d2jf00asb0fe6y.cloudfront.net/adventures-huckleberry-finn-mark-twain_07_cde90e20b3061d5df96d5387b650d076_sm.jpg",
    "repImageUrl": "https://d2jf00asb0fe6y.cloudfront.net/adventures-huckleberry-finn-mark-twain_07_cde90e20b3061d5df96d5387b650d076_rep.jpg",
  "dateCreated": "2016-04-07",
  "dct:created": "2016-04-07",
  "dateModified": "2020-07-22",
  "dct:modified": "2020-07-22",
    "about": [
        {
          "@type": "Thing",
            "disambiguatingDescription": "Subject",
          "name": "American Literature"
        },
        {
          "@type": "Thing",
            "disambiguatingDescription": "Time Period",
          "name": "Civil War and Reconstruction (1850-1877)",
            "sameAs": "http://www.nchs.ucla.edu/history-standards/us-history-content-standards/united-states-era-5"
        },
        {
          "@type": "Thing",
            "disambiguatingDescription": "Time Period",
          "name": "The Development of the Industrial United States (1870-1900)",
            "sameAs": "http://www.nchs.ucla.edu/history-standards/us-history-content-standards/united-states-era-6"
        }
    ],
    "description": "This collection uses primary sources to explore Mark Twain&#39;s The Adventures of Huckleberry Finn.",
    "author": [
        {
          "@type": "Person",
            "affiliation": {
              "@type": "Organization",
              "name": "East Central High School, St. Leon, Indiana"
            },
          "name": "Susan Ketcham"
        }
    ],
  "publisher": {
    "@id": "//dp.la/",
    "@type": "Organization",
    "name": "Digital Public Library of America",
    "email": "info@dp.la"
  },
  "hasPart": [
        {
          "@id": "https://dp.la/primary-source-sets/guides/teaching-guide-exploring-the-adventures-of-huckleberry-finn",
          "@type": "CreativeWork",
          "name": "Teaching Guide: Exploring *The Adventures of Huckleberry Finn*",
          "disambiguatingDescription": "guide"
        },
        {
          "@id": "https://dp.la/primary-source-sets/sources/1000",
          "@type": "CreativeWork",
            "thumbnailUrl": "https://d2jf00asb0fe6y.cloudfront.net/adventures-huckleberry-finn-mark-twain_01_7d40e75c893f2c0631eb9ce1824b780b_thumb.jpg",
            "repImageUrl": "https://d2jf00asb0fe6y.cloudfront.net/adventures-huckleberry-finn-mark-twain_01_7d40e75c893f2c0631eb9ce1824b780b_rep.jpg",
          "name": "A lithograph of a drawing by Henry Lewis showing Hannibal, Missouri, home of Samuel Langhorne Clemens, 1854-1857.",
          "mainEntity": [
            {
                  "@type": "ImageObject"
            }
          ],
          "disambiguatingDescription": "source"
        },
        {
          "@id": "https://dp.la/primary-source-sets/sources/1001",
          "@type": "CreativeWork",
            "thumbnailUrl": "https://d2jf00asb0fe6y.cloudfront.net/adventures-huckleberry-finn-mark-twain_02_cbfe0ff399c501e371e58daa9542bd80_thumb.jpeg",
            "repImageUrl": "https://d2jf00asb0fe6y.cloudfront.net/adventures-huckleberry-finn-mark-twain_02_cbfe0ff399c501e371e58daa9542bd80_rep.jpeg",
          "name": "A photograph of Hannibal, Missouri, home of Samuel Langhorne Clemens, ca. 1880.",
          "mainEntity": [
            {
                  "@type": "ImageObject"
            }
          ],
          "disambiguatingDescription": "source"
        },
        {
          "@id": "https://dp.la/primary-source-sets/sources/1002",
          "@type": "CreativeWork",
            "thumbnailUrl": "https://d2jf00asb0fe6y.cloudfront.net/adventures-huckleberry-finn-mark-twain_03_5b26f6787f04b426217b25b8e107147d_thumb.jpg",
            "repImageUrl": "https://d2jf00asb0fe6y.cloudfront.net/adventures-huckleberry-finn-mark-twain_03_5b26f6787f04b426217b25b8e107147d_rep.jpg",
          "name": "A reward poster for a runaway slave in Missouri, 1820-1860.",
          "mainEntity": [
            {
                  "@type": "ImageObject"
            }
          ],
          "disambiguatingDescription": "source"
        },
        {
          "@id": "https://dp.la/primary-source-sets/sources/1003",
          "@type": "CreativeWork",
            "thumbnailUrl": "https://d2jf00asb0fe6y.cloudfront.net/adventures-huckleberry-finn-mark-twain_04_ddb7d1860f7b7d46a257aafce310cb6d_thumb.jpg",
            "repImageUrl": "https://d2jf00asb0fe6y.cloudfront.net/adventures-huckleberry-finn-mark-twain_04_ddb7d1860f7b7d46a257aafce310cb6d_rep.jpg",
          "name": "A photograph of a plantation house in South Carolina, ca. 1960.",
          "mainEntity": [
            {
                  "@type": "ImageObject"
            }
          ],
          "disambiguatingDescription": "source"
        },
        {
          "@id": "https://dp.la/primary-source-sets/sources/1004",
          "@type": "CreativeWork",
            "thumbnailUrl": "https://d2jf00asb0fe6y.cloudfront.net/adventures-huckleberry-finn-mark-twain_05_c7816d18347f30ff77eae03ce9919128_thumb.jpg",
            "repImageUrl": "https://d2jf00asb0fe6y.cloudfront.net/adventures-huckleberry-finn-mark-twain_05_c7816d18347f30ff77eae03ce9919128_rep.jpg",
          "name": "A letter describing the life and times of a plantation owner before and after the Civil War, 1944.",
          "mainEntity": [
            {
                  "@type": "MediaObject"
            }
          ],
          "disambiguatingDescription": "source"
        },
        {
          "@id": "https://dp.la/primary-source-sets/sources/1005",
          "@type": "CreativeWork",
            "thumbnailUrl": "https://d2jf00asb0fe6y.cloudfront.net/adventures-huckleberry-finn-mark-twain_06_def6b8e505e91696bb407faa5441277b_thumb.jpg",
            "repImageUrl": "https://d2jf00asb0fe6y.cloudfront.net/adventures-huckleberry-finn-mark-twain_06_def6b8e505e91696bb407faa5441277b_rep.jpg",
          "name": "An excerpt from *The Black Man’s Burden or The Horrors of Southern Lynchings* about an Arkansas lynching as related by Mr. Gardner, 1902. ",
          "mainEntity": [
            {
                  "@type": "MediaObject"
            }
          ],
          "disambiguatingDescription": "source"
        },
        {
          "@id": "https://dp.la/primary-source-sets/sources/1006",
          "@type": "CreativeWork",
            "thumbnailUrl": "https://d2jf00asb0fe6y.cloudfront.net/adventures-huckleberry-finn-mark-twain_07_cde90e20b3061d5df96d5387b650d076_thumb.jpg",
            "repImageUrl": "https://d2jf00asb0fe6y.cloudfront.net/adventures-huckleberry-finn-mark-twain_07_cde90e20b3061d5df96d5387b650d076_rep.jpg",
          "name": "A 1959 pictorial map of events in *The Adventures of Huckleberry Finn*.",
          "mainEntity": [
            {
                  "@type": "ImageObject"
            }
          ],
          "disambiguatingDescription": "source"
        },
        {
          "@id": "https://dp.la/primary-source-sets/sources/1007",
          "@type": "CreativeWork",
            "thumbnailUrl": "https://d2jf00asb0fe6y.cloudfront.net/adventures-huckleberry-finn-mark-twain_08_6dab92b0dcacde0000faefb4ccbdeed1_thumb.jpg",
            "repImageUrl": "https://d2jf00asb0fe6y.cloudfront.net/adventures-huckleberry-finn-mark-twain_08_6dab92b0dcacde0000faefb4ccbdeed1_rep.jpg",
          "name": "An excerpt from a 1985 lecture titled “Born to Trouble: One-Hundred Years of Huckleberry Finn.”",
          "mainEntity": [
            {
                  "@type": "MediaObject"
            }
          ],
          "disambiguatingDescription": "source"
        },
        {
          "@id": "https://dp.la/primary-source-sets/sources/1008",
          "@type": "CreativeWork",
            "thumbnailUrl": "https://d2jf00asb0fe6y.cloudfront.net/adventures-huckleberry-finn-mark-twain_09a_2d2279aef57c934f675ce6bf4fbf88df_thumb.jpg",
            "repImageUrl": "https://d2jf00asb0fe6y.cloudfront.net/adventures-huckleberry-finn-mark-twain_09a_2d2279aef57c934f675ce6bf4fbf88df_rep.jpg",
          "name": "An essay by David Cazarez regarding the use of the n-word in Huck Finn, 2011.",
          "mainEntity": [
            {
                  "@type": "MediaObject"
            }
          ],
          "disambiguatingDescription": "source"
        },
        {
          "@id": "https://dp.la/primary-source-sets/sources/1009",
          "@type": "CreativeWork",
            "thumbnailUrl": "https://d2jf00asb0fe6y.cloudfront.net/adventures-huckleberry-finn-mark-twain_10_63474e4f3072abdea4cca59a3c6b8443_thumb.jpg",
            "repImageUrl": "https://d2jf00asb0fe6y.cloudfront.net/adventures-huckleberry-finn-mark-twain_10_63474e4f3072abdea4cca59a3c6b8443_rep.jpg",
          "name": "An original 1884 illustration by E.W. Kemble from chapter twelve, “On the Raft,” in *The Adventures of Huckleberry Finn*.",
          "mainEntity": [
            {
                  "@type": "ImageObject"
            }
          ],
          "disambiguatingDescription": "source"
        },
        {
          "@id": "https://dp.la/primary-source-sets/sources/1010",
          "@type": "CreativeWork",
            "thumbnailUrl": "https://d2jf00asb0fe6y.cloudfront.net/adventures-huckleberry-finn-mark-twain_11_1f8c36442408800567881b38e963daa0_thumb.jpg",
            "repImageUrl": "https://d2jf00asb0fe6y.cloudfront.net/adventures-huckleberry-finn-mark-twain_11_1f8c36442408800567881b38e963daa0_rep.jpg",
          "name": "A poster advertising a lecture in Brooklyn, New York, by Mark Twain, with a caricature of the author, 1873. ",
          "mainEntity": [
            {
                  "@type": "ImageObject"
            }
          ],
          "disambiguatingDescription": "source"
        },
        {
          "@id": "https://dp.la/primary-source-sets/sources/1011",
          "@type": "CreativeWork",
            "thumbnailUrl": "https://d2jf00asb0fe6y.cloudfront.net/adventures-huckleberry-finn-mark-twain_12_71f6d685dff934f30b2c55ec36e48d8b_thumb.jpg",
            "repImageUrl": "https://d2jf00asb0fe6y.cloudfront.net/adventures-huckleberry-finn-mark-twain_12_71f6d685dff934f30b2c55ec36e48d8b_rep.jpg",
          "name": "A photograph of Samuel Clemens in his iconic white suit, ca. 1909.",
          "mainEntity": [
            {
                  "@type": "ImageObject"
            }
          ],
          "disambiguatingDescription": "source"
        },
        {
          "@id": "https://dp.la/primary-source-sets/sources/1012",
          "@type": "CreativeWork",
            "thumbnailUrl": "https://d2jf00asb0fe6y.cloudfront.net/adventures-huckleberry-finn-mark-twain_13_8e75bc4a27f9681e061a55b168132489_thumb.jpg",
            "repImageUrl": "https://d2jf00asb0fe6y.cloudfront.net/adventures-huckleberry-finn-mark-twain_13_8e75bc4a27f9681e061a55b168132489_rep.jpg",
          "name": "A photograph of steamboats on the Mississippi River, ca. 1860.",
          "mainEntity": [
            {
                  "@type": "ImageObject"
            }
          ],
          "disambiguatingDescription": "source"
        },
        {
          "@id": "https://dp.la/primary-source-sets/sources/1013",
          "@type": "CreativeWork",
            "thumbnailUrl": "https://d2jf00asb0fe6y.cloudfront.net/adventures-huckleberry-finn-mark-twain_14_0e190fa51aa56017b4139edeb9a151bc_thumb.jpg",
            "repImageUrl": "https://d2jf00asb0fe6y.cloudfront.net/adventures-huckleberry-finn-mark-twain_14_0e190fa51aa56017b4139edeb9a151bc_rep.jpg",
          "name": "An illustration of the levee at Cairo, Illinois, 1874.",
          "mainEntity": [
            {
                  "@type": "ImageObject"
            }
          ],
          "disambiguatingDescription": "source"
        },
        {
          "@id": "https://dp.la/primary-source-sets/sources/1014",
          "@type": "CreativeWork",
            "thumbnailUrl": "https://d2jf00asb0fe6y.cloudfront.net/adventures-huckleberry-finn-mark-twain_15_23687ed3133d95505da022ed8b8e9060_thumb.jpg",
            "repImageUrl": "https://d2jf00asb0fe6y.cloudfront.net/adventures-huckleberry-finn-mark-twain_15_23687ed3133d95505da022ed8b8e9060_rep.jpg",
          "name": "An excerpt from a book that includes an extensive list of superstitions, 1907.",
          "mainEntity": [
            {
                  "@type": "MediaObject"
            }
          ],
          "disambiguatingDescription": "source"
        },
      {
        "name": "Resources",
        "text": "1. [The Mark Twain House \u0026 Museum](https://www.marktwainhouse.org/). \r\n2. [Culture Shock: Huck Finn in Context Teaching Guide](http://www.pbs.org/wgbh/cultureshock/teachers/huck/index.html), PBS. \r\n3. “[Mark Twain’s Huckleberry Finn: Controversy at the Heart of a Classic](https://blogs.loc.gov/teachers/2013/11/mark-twains-huckleberry-finn-controversy-at-the-heart-of-a-classic/),” Teaching with the Library of Congress blog. \r\n4. [The Adventures of Huckleberry Finn](http://twain.lib.virginia.edu/huckfinn/huchompg.html), Mark Twain in his Times digital archive, University of Virginia Department of English. "
      },
      {
        "name": "Overview",
        "text": "Published in 1885, Mark Twain’s *The Adventures of Huckleberry Finn* remains an American classic taught in thousands of classrooms across the country. While the book seems like a novel of adventure, *The Adventures of Huckleberry Finn* is at heart a satire in which Twain examines “civilization” and freedom in the pre-Civil War South. *The Adventures of Huckleberry Finn* was first banned a month after its publication as “not suitable for trash” and it remains number fourteen on the most banned list. Twain’s prolific use of the n-word is especially controversial. However, Jim—Huck’s companion and a runaway slave—is arguably the hero in the novel because of his leadership and sacrifice, despite the fact that Twain narrates his story through Huck’s voice. From the perspective of Huck, a poor, uneducated orphan, Twain’s commentary on race relations, the Southern justice system, class division, and senseless violence has resonated for over 130 years. This primary source set includes portraits, illustrations, documents, and photographs that provide context for historical and thematic elements in *The Adventures of Huckleberry Finn*."
      }
  ],
    "isRelatedTo": [
        {
          "@id": "https://dp.la/primary-source-sets/sets/theodore-dreiser-s-sister-carrie-and-the-urbanization-of-chicago",
            "thumbnailUrl": "https://d2jf00asb0fe6y.cloudfront.net/theodore-dreiser_05_397147adf0d4238d3c7d7f9d7d15e3fe_sm.jpg",
            "repImageUrl": "https://d2jf00asb0fe6y.cloudfront.net/theodore-dreiser_05_397147adf0d4238d3c7d7f9d7d15e3fe_rep.jpg",
          "name": "Theodore Dreiser’s *Sister Carrie* and the Urbanization of Chicago"
        },
        {
          "@id": "https://dp.la/primary-source-sets/sets/incidents-in-the-life-of-a-slave-girl-by-harriet-jacobs",
            "thumbnailUrl": "https://d2jf00asb0fe6y.cloudfront.net/incidents-life-slave-girl-harriet-jacobs_06_f472749a56642ccb944c04d857d2f185_sm.jpg",
            "repImageUrl": "https://d2jf00asb0fe6y.cloudfront.net/incidents-life-slave-girl-harriet-jacobs_06_f472749a56642ccb944c04d857d2f185_rep.jpg",
          "name": "*Incidents in the Life of a Slave Girl* by Harriet Jacobs"
        },
        {
          "@id": "https://dp.la/primary-source-sets/sets/beloved-by-toni-morrison",
            "thumbnailUrl": "https://d2jf00asb0fe6y.cloudfront.net/beloved-toni-morrison_08_60e29a1c3983f2b1a077750352d7ad30_sm.jpg",
            "repImageUrl": "https://d2jf00asb0fe6y.cloudfront.net/beloved-toni-morrison_08_60e29a1c3983f2b1a077750352d7ad30_rep.jpg",
          "name": "*Beloved* by Toni Morrison"
        },
        {
          "@id": "https://dp.la/primary-source-sets/sets/uncle-tom-s-cabin-by-harriet-beecher-stowe",
            "thumbnailUrl": "https://d2jf00asb0fe6y.cloudfront.net/uncle-toms-cabin-harriet-beecher-stowe_00_529f51e7ae782956e47f5ce8288bff17.jpg",
            "repImageUrl": "https://d2jf00asb0fe6y.cloudfront.net/uncle-toms-cabin-harriet-beecher-stowe_00_529f51e7ae782956e47f5ce8288bff17_rep.jpg",
          "name": "*Uncle Tom's Cabin* by Harriet Beecher Stowe"
        },
        {
          "@id": "https://dp.la/primary-source-sets/sets/little-women-by-louisa-may-alcott",
            "thumbnailUrl": "https://d2jf00asb0fe6y.cloudfront.net/little-women-louisa-may-alcott_00_eed0d959d47a589b8958e254d4131ddf.jpg",
            "repImageUrl": "https://d2jf00asb0fe6y.cloudfront.net/little-women-louisa-may-alcott_00_eed0d959d47a589b8958e254d4131ddf_rep.jpg",
          "name": "*Little Women* by Louisa May Alcott"
        }
    ],
  "inLanguage": [
    {
      "@id": "http://lexvo.org/id/term/eng/English",
      "@type": "Language",
      "name": "English"
    }
  ],
  "learningResourceType": "Source Set",
  "license": "http://dp.la/info/terms/",
  "typicalAgeRange": "11-18",
  "accessbilityFeature": [
    "captions",
    "structuralNavigation",
    "audioControl",
    "videoControl"
  ],
  "accessibilityHazard": [
    "noFlashingHazard",
    "motionSimulation",
    "noSoundHazard"
  ],
  "accessibilityControl": [
    "fullMouseControl"
  ],
  "educationalAlignment": [
    {
      "@type": "AlignmentObject",
      "alignmentType": "requires",
      "educationalFramework": "Common Core State Standards",
      "targetName": "CCSS.ELA-Literacy.RH.6-8.7",
      "targetUrl": "ccss:ELA-Literacy/RH/6-8/7/"
    },
    {
      "@type": "AlignmentObject",
      "alignmentType": "requires",
      "educationalFramework": "Common Core State Standards",
      "targetName": "CCSS.ELA-Literacy.RH.6-8.7",
      "targetUrl": "ccss:ELA-Literacy/RH/6-8/7/"
    },
    {
      "@type": "AlignmentObject",
      "alignmentType": "requires",
      "educationalFramework": "Common Core State Standards",
      "targetName": "CCSS.ELA-Literacy.RH.6-8.9",
      "targetUrl": "ccss:ELA-Literacy/RH/6-8/9/"
    },
    {
      "@type": "AlignmentObject",
      "alignmentType": "requires",
      "educationalFramework": "Common Core State Standards",
      "targetName": "CCSS.ELA-Literacy.RH.9-10.9",
      "targetUrl": "ccss:ELA-Literacy/RH/9-10/9/"
    },
    {
      "@type": "AlignmentObject",
      "alignmentType": "requires",
      "educationalFramework": "Common Core State Standards",
      "targetName": "CCSS.ELA-Literacy.RH.11-12.7",
      "targetUrl": "ccss:ELA-Literacy/RH/11-12/7/"
    },
    {
      "@type": "AlignmentObject",
      "alignmentType": "requires",
      "educationalFramework": "Common Core State Standards",
      "targetName": "CCSS.ELA-Literacy.RH.11-12.9",
      "targetUrl": "ccss:ELA-Literacy/RH/11-12/9/"
    },
    {
      "@type": "AlignmentObject",
      "alignmentType": "requires",
      "educationalFramework": "Common Core State Standards",
      "targetName": "CCSS.ELA-Literacy.CCRA.R.7",
      "targetUrl": "ccss:ELA-Literacy/CCRA/R/7/"
    },
    {
      "@type": "AlignmentObject",
      "alignmentType": "requires",
      "educationalFramework": "Common Core State Standards",
      "targetName": "CCSS.ELA-Literacy.CCRA.W.8",
      "targetUrl": "ccss:ELA-Literacy/CCRA/W/8/"
    },
    {
      "@type": "AlignmentObject",
      "alignmentType": "requires",
      "educationalFramework": "Common Core State Standards",
      "targetName": "CCSS.ELA-Literacy.WHST.6-8.8",
      "targetUrl": "ccss:ELA-Literacy/WHST/6-8/8/"
    },
    {
      "@type": "AlignmentObject",
      "alignmentType": "requires",
      "educationalFramework": "Common Core State Standards",
      "targetName": "CCSS.ELA-Literacy.WHST.9-10.8",
      "targetUrl": "ccss:ELA-Literacy/WHST/9-10/8/"
    },
    {
      "@type": "AlignmentObject",
      "alignmentType": "requires",
      "educationalFramework": "Common Core State Standards",
      "targetName": "CCSS.ELA-Literacy.WHST.11-12.8",
      "targetUrl": "ccss:ELA-Literacy/WHST/11-12/8/"
    }
  ]
}
