{
  "@context": {
    "@vocab": "http://schema.org/",
    "ccss": "http://www.corestandards.org/",
    "dct": "http://purl.org/dc/terms/",
    "dcmitype": "http://purl.org/dc/dcmitype/",
    "edm": "http://www.europeana.eu/schemas/edm",
    "ore": "http://www.openarchives.org/ore/terms/",
    "text": {
      "@id": "http://schema.org/text",
      "@type": "http://ns.ontowiki.net/SysOnt/Markdown"
    },
    "name": {
      "@id": "http://schema.org/text",
      "@type": "http://ns.ontowiki.net/SysOnt/Markdown"
    }
  },
  "@id": "https://dp.la/primary-source-sets/sources/1533",
  "@type": "CreativeWork",
  "thumbnailUrl": "https://d2jf00asb0fe6y.cloudfront.net/panic-1837_10_5dcb9c70f7f093dfd0b3752e28e181f4_thumb.jpg",
  "repImageUrl": "https://d2jf00asb0fe6y.cloudfront.net/panic-1837_10_5dcb9c70f7f093dfd0b3752e28e181f4_rep.jpg",
  "name": "A receipt for the sale of twenty four bales of cotton sold on behalf of Aaron Spell, March 25, 1836.",
  "dateCreated": "2017-09-21",
  "dct:created": "2017-09-21",
  "dateModified": "2017-09-26",
  "dct:modified": "2017-09-26",
  "mainEntity": [
    {
      "@type": "MediaObject",
      "associatedMedia": [
        {
          "fileFormat": "pdf",
          "contentUrl": "panic-1837_10_5dcb9c70f7f093dfd0b3752e28e181f4.pdf"
        }
      ],
      "citation": [
        {
          "@type": "CreativeWork",
          "text": "Courtesy of Mississippi State University Libraries via Digital Library of Georgia.",
          "disabmiguationDescription": "credits"
        },
        {
          "@type": "CreativeWork",
          "text": "Leigh Maddox & Co., \u201cAaron Spell Wilkinson Account, 1836,\u201d Digital Public Library of America, https://dp.la/item/d6a3d383e56b13a025bbbc65f59d992e. ",
          "disabmiguationDescription": "citation"
        }
      ]
    }
  ],
  "text": "This document and the following document are receipts for cotton sold on behalf of cotton planter Aaron Spell on two separate occasions, one before the panic, in 1836, and one during the panic, in 1840. On this receipt, the numbers in columns represent bale numbers and weights. The total weight is then multiplied by the price paid per pound of cotton, in this case seventeen cents per pound for the first group of fifteen bales, and sixteen cents per pound for the second group of nine bales. Varying sale prices may suggest that some of the cotton was better quality than the rest. The notes at the bottom of the receipt detail additional charges deducted from the total sale price, such as shipping, storage, insurance, and broker\u2019s fees.\r\n\r\nTranscription:\r\n\r\nSale 24 Bales Cotton by order and for account of Aaron Spell Esq.\r\n\r\nSold N N Wilkinson<br/>\r\nA Spell\t\r\n\r\n[Column 1 top]<br/>\r\nBale 7; Weight: 440<br/>\r\nBale 28; Weight 434<br/>\r\nBale 14; Weight 406<br/>\r\nBale 10; Weight 412<br/>\r\nBale 4; Weight 492<br/>\r\nBale 23; Weight 400<br/>\r\nBale 17; Weight 433<br/>\r\nBale 9; Weight 400<br/>\r\nBale 16; Weight 378<br/>\r\nBale 21; Weight 425\r\n\r\n[Column 2 top]<br/>\r\nBale 18; Weight 454 <br/>\r\nBale 2; Weight 423 <br/>\r\nBale 13; Weight 430 <br/>\r\nBale 8; Weight 430<br/>\r\nBale 15; Weight 423\r\n\r\n4223 [+] 2160 [=] 6383 @ 17\u00a2 [=]  $1085.11<br/>\r\n(Total weight from column 1 top plus total weight from column 2 top)\r\n\r\n[Column 1 bottom]<br/>\r\nBale 20; Weight 421<br/>\r\nBale 19; Weight 420<br/>\r\nBale 1; Weight 382<br/>\r\nBale 25; Weight 411<br/>\r\nBale 3; Weight 416\t\t\r\n\r\n[Column 2 bottom]<br/>\r\nBale 26 / Weigt 420<br/>\r\nBale 24 / Weight 406<br/>\r\nBale 5 / Weight 455<br/>\r\nBale 2 / Weight 407\r\n\r\n2050 [+] 1688\t[=] 3738 @ 16\u00a2 [=]   $598.08 <br/>      \r\n(Total weight from column 1 bottom plus total weight from column 2 bottom)\r\n\r\n[Sum of sale prices from top and bottom columns =] $1683.19\r\n\r\nCharges\r\n\r\nPaid freight at $1.25 per bale...$30.00<br/>\r\n[Paid] River Insurance on  $70 \u201c[per bale]\u201d [at] \u00be% [+] Pol[???] $1...13.60<br/>\r\n[Paid River Insurance agent] fire @ \u00bc% [of $1683.19]... 4.21\t<br/>\r\n[Paid] Drayage Storage Labor and Weighing @ 50 \u00a2 [per bale]...12.00<br/>\r\nCommission 2 \u00bd...42.08 \t<br/>\r\n[Sum of Charges =] 101.89\r\n\r\nNet Proceeds Dollars $1581.30 <br/>\r\nE + OE Due in cash 5 April <br/>\r\nNew Orleans\t26 March 1836 for Leigh Maddux & C.\r\n\r\nM. Conway",
  "isRelatedTo": [
    {
      "thumbnailUrl": "https://d2jf00asb0fe6y.cloudfront.net/panic-1837_11_5dcb9c70f7f093dfd0b3752e28e181f4_thumb.jpg",
      "repImageUrl": "https://d2jf00asb0fe6y.cloudfront.net/panic-1837_11_5dcb9c70f7f093dfd0b3752e28e181f4_rep.jpg",
      "name": "A receipt for the sale of thirty bales of cotton sold on behalf of Aaron Spell, February 9, 1840.",
      "@id": "https://dp.la/primary-source-sets/sources/1534"
    },
    {
      "thumbnailUrl": "https://d2jf00asb0fe6y.cloudfront.net/panic-1837_12_70848a5284f1d7eb835d18845038042d_thumb.jpg",
      "repImageUrl": "https://d2jf00asb0fe6y.cloudfront.net/panic-1837_12_70848a5284f1d7eb835d18845038042d_rep.jpg",
      "name": "A court document recording the settlement of a debt owed by Lancaster McNay through the transfer of five enslaved women and girls, 1839.",
      "@id": "https://dp.la/primary-source-sets/sources/1535"
    },
    {
      "thumbnailUrl": "https://d2jf00asb0fe6y.cloudfront.net/panic-1837_01_b164a728cb23c90c22d6e562b04d37d6_thumb.jpg",
      "repImageUrl": "https://d2jf00asb0fe6y.cloudfront.net/panic-1837_01_b164a728cb23c90c22d6e562b04d37d6_rep.jpg",
      "name": "A letter from the cashier at Mohawk Bank in Schenectady, New York to William Hayes about a deposit to his account, 1834.",
      "@id": "https://dp.la/primary-source-sets/sources/1524"
    },
    {
      "thumbnailUrl": "https://d2jf00asb0fe6y.cloudfront.net/panic-1837_02_352b22c62314cc50a42f1a42e40d9920_thumb.jpg",
      "repImageUrl": "https://d2jf00asb0fe6y.cloudfront.net/panic-1837_02_352b22c62314cc50a42f1a42e40d9920_rep.jpg",
      "name": "A five-dollar bill issued by Kirtland Safety Society Bank of Kirtland, Ohio, 1837.",
      "@id": "https://dp.la/primary-source-sets/sources/1525"
    },
    {
      "thumbnailUrl": "https://d2jf00asb0fe6y.cloudfront.net/panic-1837_03_a560e20356ccefb5a5d9e8a86fb32823_thumb.jpg",
      "repImageUrl": "https://d2jf00asb0fe6y.cloudfront.net/panic-1837_03_a560e20356ccefb5a5d9e8a86fb32823_rep.jpg",
      "name": "A revolving table tool designed to calculate interest rates, 1839.",
      "@id": "https://dp.la/primary-source-sets/sources/1526"
    },
    {
      "thumbnailUrl": "https://d2jf00asb0fe6y.cloudfront.net/panic-1837_04_826167643834faa2cf931c4615552617_thumb.jpg",
      "repImageUrl": "https://d2jf00asb0fe6y.cloudfront.net/panic-1837_04_826167643834faa2cf931c4615552617_rep.jpg",
      "name": "An excerpt from *Sylvester's Bank Note and Exchange Manual*, 1833",
      "@id": "https://dp.la/primary-source-sets/sources/1527"
    },
    {
      "thumbnailUrl": "https://d2jf00asb0fe6y.cloudfront.net/panic-1837_05_a3572421fd7561cc0d242d17b6e4ec30_thumb.jpg",
      "repImageUrl": "https://d2jf00asb0fe6y.cloudfront.net/panic-1837_05_a3572421fd7561cc0d242d17b6e4ec30_rep.jpg",
      "name": "Excerpts from *The Pocket Cambist*, a guide for exchanging currency between countries, 1836.",
      "@id": "https://dp.la/primary-source-sets/sources/1528"
    },
    {
      "thumbnailUrl": "https://d2jf00asb0fe6y.cloudfront.net/panic-1837_06_dc6ea846c0367dd7e86b0a3a597a0190_thumb.jpg",
      "repImageUrl": "https://d2jf00asb0fe6y.cloudfront.net/panic-1837_06_dc6ea846c0367dd7e86b0a3a597a0190_rep.jpg",
      "name": "A political cartoon representing negative public opinion and political opposition to the agenda of President Andrew Jackson, circa 1832.",
      "@id": "https://dp.la/primary-source-sets/sources/1529"
    },
    {
      "thumbnailUrl": "https://d2jf00asb0fe6y.cloudfront.net/panic-1837_07_afa23a335d05126e9aa5ae23c7ab8295_thumb.jpg",
      "repImageUrl": "https://d2jf00asb0fe6y.cloudfront.net/panic-1837_07_afa23a335d05126e9aa5ae23c7ab8295_rep.jpg",
      "name": "A political cartoon issued in July 1837 that depicts a New York City street scene demonstrating the impact of the Panic of 1837.",
      "@id": "https://dp.la/primary-source-sets/sources/1530"
    },
    {
      "thumbnailUrl": "https://d2jf00asb0fe6y.cloudfront.net/panic-1837_08_11f35a933881202ff7acf8587ec8cf06_thumb.jpg",
      "repImageUrl": "https://d2jf00asb0fe6y.cloudfront.net/panic-1837_08_11f35a933881202ff7acf8587ec8cf06_rep.jpg",
      "name": "An excerpt from an 1834 pamphlet with arguments from New York businessmen about effects of removing federal money from the national bank.",
      "@id": "https://dp.la/primary-source-sets/sources/1531"
    },
    {
      "thumbnailUrl": "https://d2jf00asb0fe6y.cloudfront.net/panic-1837_09_68fd883a8ff984b7d378a75882247c0a_thumb.jpg",
      "repImageUrl": "https://d2jf00asb0fe6y.cloudfront.net/panic-1837_09_68fd883a8ff984b7d378a75882247c0a_rep.jpg",
      "name": "An 1841 token alluding to \u201chard times,\u201d or the Panic of 1837, and targeting the policies of President Van Buren.",
      "@id": "https://dp.la/primary-source-sets/sources/1532"
    }
  ],
  "isPartOf": {
    "@id": "https://dp.la/primary-source-sets/sets/the-panic-of-1837",
    "@type": "CreativeWork",
    "name": "The Panic of 1837"
  }
}
