{
  "@context": {
  "@vocab": "http://schema.org/",
  "ccss": "http://www.corestandards.org/",
  "dct": "http://purl.org/dc/terms/",
  "dcmitype": "http://purl.org/dc/dcmitype/",
  "edm": "http://www.europeana.eu/schemas/edm",
  "ore": "http://www.openarchives.org/ore/terms/",
  "text": {
    "@id": "http://schema.org/text",
    "@type": "http://ns.ontowiki.net/SysOnt/Markdown"
  },
  "name": {
    "@id": "http://schema.org/text",
    "@type": "http://ns.ontowiki.net/SysOnt/Markdown"
  }
}
,
  "@id": "https://dp.la/primary-source-sets/sets/commodore-perry-s-expedition-to-japan",
  "@type": "CreativeWork",
  "dct:type": "dcmitype:InteractiveResource",
  "name": "Commodore Perry’s Expedition to Japan",
    "thumbnailUrl": "https://d2jf00asb0fe6y.cloudfront.net/commodore-perry_07a_1b7ea66200ccd4d6db13f970dbda21ed_sm.jpg",
    "repImageUrl": "https://d2jf00asb0fe6y.cloudfront.net/commodore-perry_07a_1b7ea66200ccd4d6db13f970dbda21ed_rep.jpg",
  "dateCreated": "2018-02-22",
  "dct:created": "2018-02-22",
  "dateModified": "2018-02-28",
  "dct:modified": "2018-02-28",
    "about": [
        {
          "@type": "Thing",
            "disambiguatingDescription": "Subject",
          "name": "US History"
        },
        {
          "@type": "Thing",
            "disambiguatingDescription": "Time Period",
          "name": "Expansion and Reform (1801-1861)",
            "sameAs": "http://www.nchs.ucla.edu/history-standards/us-history-content-standards/united-states-era-4"
        },
        {
          "@type": "Thing",
            "disambiguatingDescription": "Subject",
          "name": "World History"
        }
    ],
    "description": "This collection uses primary sources to explore Commodore Matthew C. Perry&#39;s expedition to Japan in 1853.",
    "author": [
        {
          "@type": "Person",
            "affiliation": {
              "@type": "Organization",
              "name": "Ripley High School, West Virginia"
            },
          "name": "Adena Barnette"
        }
    ],
  "publisher": {
    "@id": "//dp.la/",
    "@type": "Organization",
    "name": "Digital Public Library of America",
    "email": "info@dp.la"
  },
  "hasPart": [
        {
          "@id": "https://dp.la/primary-source-sets/guides/teaching-guide-exploring-commodore-perry-s-expedition-to-japan",
          "@type": "CreativeWork",
          "name": "Teaching Guide: Exploring Commodore Perry’s Expedition to Japan",
          "disambiguatingDescription": "guide"
        },
        {
          "@id": "https://dp.la/primary-source-sets/sources/1789",
          "@type": "CreativeWork",
            "thumbnailUrl": "https://d2jf00asb0fe6y.cloudfront.net/commodore-perry_01_c27fbcdf1d5defae0b9f2626d89a50de_thumb.jpg",
            "repImageUrl": "https://d2jf00asb0fe6y.cloudfront.net/commodore-perry_01_c27fbcdf1d5defae0b9f2626d89a50de_rep.jpg",
          "name": "A photograph of Commodore Matthew Perry after his expedition to Japan, ca. 1855.",
          "mainEntity": [
            {
                  "@type": "ImageObject"
            }
          ],
          "disambiguatingDescription": "source"
        },
        {
          "@id": "https://dp.la/primary-source-sets/sources/1790",
          "@type": "CreativeWork",
            "thumbnailUrl": "https://d2jf00asb0fe6y.cloudfront.net/commodore-perry_02_94247f4795791cb33a24665a2b8533b8_thumb.jpg",
            "repImageUrl": "https://d2jf00asb0fe6y.cloudfront.net/commodore-perry_02_94247f4795791cb33a24665a2b8533b8_rep.jpg",
          "name": "A Japanese woodcut of Commodore Matthew Perry.",
          "mainEntity": [
            {
                  "@type": "ImageObject"
            }
          ],
          "disambiguatingDescription": "source"
        },
        {
          "@id": "https://dp.la/primary-source-sets/sources/1791",
          "@type": "CreativeWork",
            "thumbnailUrl": "https://d2jf00asb0fe6y.cloudfront.net/commodore-perry_03_141ce0f7ead5ed36454d9d3ae5bf1285_thumb.jpg",
            "repImageUrl": "https://d2jf00asb0fe6y.cloudfront.net/commodore-perry_03_141ce0f7ead5ed36454d9d3ae5bf1285_rep.jpg",
          "name": "A series of six color lithographs by Wilhelm Heine and Eliphalet Brown documenting the Japanese expedition under Commodore Perry, 1855.",
          "mainEntity": [
            {
                  "@type": "MediaObject"
            }
          ],
          "disambiguatingDescription": "source"
        },
        {
          "@id": "https://dp.la/primary-source-sets/sources/1792",
          "@type": "CreativeWork",
            "thumbnailUrl": "https://d2jf00asb0fe6y.cloudfront.net/commodore-perry_04_e977f48796b1fd23614fc717f13ab880_thumb.jpg",
            "repImageUrl": "https://d2jf00asb0fe6y.cloudfront.net/commodore-perry_04_e977f48796b1fd23614fc717f13ab880_rep.jpg",
          "name": "Three illustrations from the Perry Scroll, created by Hibata Ōsuke to celebrate the signing of the Kanagawa Treaty, 1858.",
          "mainEntity": [
            {
                  "@type": "ImageObject"
            }
          ],
          "disambiguatingDescription": "source"
        },
        {
          "@id": "https://dp.la/primary-source-sets/sources/1793",
          "@type": "CreativeWork",
            "thumbnailUrl": "https://d2jf00asb0fe6y.cloudfront.net/commodore-perry_05_36e061dbad35b4706866879041c6e07f_thumb.jpg",
            "repImageUrl": "https://d2jf00asb0fe6y.cloudfront.net/commodore-perry_05_36e061dbad35b4706866879041c6e07f_rep.jpg",
          "name": "Six illustrations documenting the arrival of foreign ships in Japan from an art catalog titled *Foreigners in Early Japan*.",
          "mainEntity": [
            {
                  "@type": "ImageObject"
            }
          ],
          "disambiguatingDescription": "source"
        },
        {
          "@id": "https://dp.la/primary-source-sets/sources/1794",
          "@type": "CreativeWork",
            "thumbnailUrl": "https://d2jf00asb0fe6y.cloudfront.net/commodore-perry_06_b436ecd74ee1c23af239fa9a5ce562a9_thumb.jpg",
            "repImageUrl": "https://d2jf00asb0fe6y.cloudfront.net/commodore-perry_06_b436ecd74ee1c23af239fa9a5ce562a9_rep.jpg",
          "name": "A Japanese illustrated map and chart depicting Commodore Perry’s arrival in Tokyo Bay.",
          "mainEntity": [
            {
                  "@type": "ImageObject"
            }
          ],
          "disambiguatingDescription": "source"
        },
        {
          "@id": "https://dp.la/primary-source-sets/sources/1795",
          "@type": "CreativeWork",
            "thumbnailUrl": "https://d2jf00asb0fe6y.cloudfront.net/commodore-perry_07_1b7ea66200ccd4d6db13f970dbda21ed_thumb.jpg",
            "repImageUrl": "https://d2jf00asb0fe6y.cloudfront.net/commodore-perry_07_1b7ea66200ccd4d6db13f970dbda21ed_rep.jpg",
          "name": "A woodblock illustration titled America by Japanese artist Utagawa Yoshitora, 1867.",
          "mainEntity": [
            {
                  "@type": "ImageObject"
            }
          ],
          "disambiguatingDescription": "source"
        },
        {
          "@id": "https://dp.la/primary-source-sets/sources/1796",
          "@type": "CreativeWork",
            "thumbnailUrl": "https://d2jf00asb0fe6y.cloudfront.net/commodore-perry_08_8a64b00808ac30adf619d1e43a951cfb_thumb.jpg",
            "repImageUrl": "https://d2jf00asb0fe6y.cloudfront.net/commodore-perry_08_8a64b00808ac30adf619d1e43a951cfb_rep.jpg",
          "name": "An excerpt from *The Americans in Japan* by Robert Tomes about the initial encounter between Perry and the Japanese, 1857.",
          "mainEntity": [
            {
                  "@type": "MediaObject"
            }
          ],
          "disambiguatingDescription": "source"
        },
        {
          "@id": "https://dp.la/primary-source-sets/sources/1797",
          "@type": "CreativeWork",
            "thumbnailUrl": "https://d2jf00asb0fe6y.cloudfront.net/commodore-perry_09_6514cd35c500017c51f02b0803f46c3c_thumb.jpg",
            "repImageUrl": "https://d2jf00asb0fe6y.cloudfront.net/commodore-perry_09_6514cd35c500017c51f02b0803f46c3c_rep.jpg",
          "name": "The Treaty of Kanagawa, signed in 1854 between the Japanese and Americans.",
          "mainEntity": [
            {
                  "@type": "MediaObject"
            }
          ],
          "disambiguatingDescription": "source"
        },
        {
          "@id": "https://dp.la/primary-source-sets/sources/1798",
          "@type": "CreativeWork",
            "thumbnailUrl": "https://d2jf00asb0fe6y.cloudfront.net/commodore-perry_10_00ff77351c6084528cddb07eef320cb5_thumb.jpg",
            "repImageUrl": "https://d2jf00asb0fe6y.cloudfront.net/commodore-perry_10_00ff77351c6084528cddb07eef320cb5_rep.jpg",
          "name": "A set of writing paper gifted to Commodore Perry by the Japanese, 1854.",
          "mainEntity": [
            {
                  "@type": "ImageObject"
            }
          ],
          "disambiguatingDescription": "source"
        },
        {
          "@id": "https://dp.la/primary-source-sets/sources/1799",
          "@type": "CreativeWork",
            "thumbnailUrl": "https://d2jf00asb0fe6y.cloudfront.net/commodore-perry_11_0876457a1bfdf583447be95f8d66670c_thumb.jpg",
            "repImageUrl": "https://d2jf00asb0fe6y.cloudfront.net/commodore-perry_11_0876457a1bfdf583447be95f8d66670c_rep.jpg",
          "name": "A porcelain dish gifted to Commodore Perry by the Japanese, 1854.",
          "mainEntity": [
            {
                  "@type": "ImageObject"
            }
          ],
          "disambiguatingDescription": "source"
        },
        {
          "@id": "https://dp.la/primary-source-sets/sources/1800",
          "@type": "CreativeWork",
            "thumbnailUrl": "https://d2jf00asb0fe6y.cloudfront.net/commodore-perry_12_b2c245c406c8fa0898f108a469ccd226_thumb.jpg",
            "repImageUrl": "https://d2jf00asb0fe6y.cloudfront.net/commodore-perry_12_b2c245c406c8fa0898f108a469ccd226_rep.jpg",
          "name": "A hand-painted fan gifted to Commodore Perry by the Japanese, 1853.",
          "mainEntity": [
            {
                  "@type": "ImageObject"
            }
          ],
          "disambiguatingDescription": "source"
        },
        {
          "@id": "https://dp.la/primary-source-sets/sources/1801",
          "@type": "CreativeWork",
            "thumbnailUrl": "https://d2jf00asb0fe6y.cloudfront.net/commodore-perry_13_ef939c86e0edd2d3fe5127eae173ff93_thumb.jpg",
            "repImageUrl": "https://d2jf00asb0fe6y.cloudfront.net/commodore-perry_13_ef939c86e0edd2d3fe5127eae173ff93_rep.jpg",
          "name": "A lacquerware picnic box gifted to Commodore Perry by the Japanese, ca. 1853.",
          "mainEntity": [
            {
                  "@type": "ImageObject"
            }
          ],
          "disambiguatingDescription": "source"
        },
      {
        "name": "Resources",
        "text": "1. [Commodore Perry and Japan (1853-1854)](http://afe.easia.columbia.edu/special/japan_1750_perry.htm), Asia for Educators, Columbia University. \r\n2. “[Scroll displays the human side of Perry’s arrival](http://www.japantimes.co.jp/culture/2013/04/18/arts/scroll-displays-the-human-side-of-perrys-arrival/#.V5Odpo7UT6l),” *The Japan Times*, April 18, 2013. \r\n3. [Perry in Japan: A Visual History](http://library.brown.edu/cds/perry/about.html), Brown University Library. \r\n4. [Treaty of Kanagawa](https://www.archives.gov/exhibits/featured_documents/treaty_of_kanagawa/), National Archives and Records Administration. \r\n5. “[How Strong Is the U.S.-Japan Relationship](http://foreignpolicy.com/2015/04/14/united-states-japan-relationship-poll-washington-tokyo/)?” *Foreign Policy*, April 14, 2015. "
      },
      {
        "name": "Overview",
        "text": "The United States experienced extensive economic and geographical expansion during the 1840s, as the spirit of [Manifest Destiny](https://dp.la/primary-source-sets/sets/manifest-destiny) drove Americans west across the North American continent to exert their influence over new places and peoples. Influenced by this expansionary philosophy, political leaders sought to expand American trade relationships worldwide. One of the first targets of this campaign was to open diplomatic and trade relations with isolationist Japan, which had been closed to western traders for centuries. In 1852, President Millard Fillmore ordered Commodore Matthew C. Perry to lead an expedition to secure Japanese trade and access to Japan’s ports for American ships. \r\n\r\nPerry’s fleet, the *Susquehanna*, *Mississippi*, *Plymouth*, and *Saratoga*, carried 400 sailors and arrived in Edo Bay, today’s Tokyo Bay, on July 8, 1853. Upon arrival, Commodore Perry asserted his military authority to intimidate the Japanese into negotiations. For example, Perry refused to speak with any Japanese officials who did not seem to be of high enough rank. When they disembarked on July 14, Perry delivered a letter from President Fillmore to the emperor of Japan describing American interests in opening trade and outlining mutual benefits. Perry and his fleet departed for several months to allow the Japanese to consider the trade proposal. \r\n\r\nPerry returned to Tokyo in March 1854 with ten ships and 1,600 men. The Japanese reluctantly agreed to American demands by signing the Kanagawa Treaty, which opened some ports to American ships and allowed for the establishment of an American consulate. Before leaving, the American delegation and the Japanese exchanged gifts, which Perry brought back to the United States. Perry’s expedition and the Kanagawa Treaty effectively ended Japan’s centuries-long isolation, especially as over twenty European nations negotiated similar treaties with Japan over the following years. In 1858, American diplomat Townsend Harris ventured to Japan to negotiate a much more comprehensive treaty. The opening of Japan, which represents an international manifestation of Manifest Destiny, established markets for American goods outside the nation’s borders and spurred the westernization of Japan. "
      }
  ],
    "isRelatedTo": [
        {
          "@id": "https://dp.la/primary-source-sets/sets/victorian-era",
            "thumbnailUrl": "https://d2jf00asb0fe6y.cloudfront.net/victorian-era_06_4bfa2555906d65e472d862ba7caec770_sm.jpg",
            "repImageUrl": "https://d2jf00asb0fe6y.cloudfront.net/victorian-era_06_4bfa2555906d65e472d862ba7caec770_rep.jpg",
          "name": "Victorian Era"
        },
        {
          "@id": "https://dp.la/primary-source-sets/sets/texas-revolution",
            "thumbnailUrl": "https://d2jf00asb0fe6y.cloudfront.net/texas-revolution_14_f7deadb49786cc32b33cd8d361db08a0_sm.jpg",
            "repImageUrl": "https://d2jf00asb0fe6y.cloudfront.net/texas-revolution_14_f7deadb49786cc32b33cd8d361db08a0_rep.jpg",
          "name": "Texas Revolution"
        },
        {
          "@id": "https://dp.la/primary-source-sets/sets/cotton-gin-and-the-expansion-of-slavery",
            "thumbnailUrl": "https://d2jf00asb0fe6y.cloudfront.net/cotton-gin_02_84f0ff53a04e2536d1f59de01fabb2b6_sm.jpg",
            "repImageUrl": "https://d2jf00asb0fe6y.cloudfront.net/cotton-gin_02_84f0ff53a04e2536d1f59de01fabb2b6_rep.jpg",
          "name": "Cotton Gin and the Expansion of Slavery"
        },
        {
          "@id": "https://dp.la/primary-source-sets/sets/california-gold-rush",
            "thumbnailUrl": "https://d2jf00asb0fe6y.cloudfront.net/california-gold-rush_07_5c95a64ae569a2071d1bdf5a308f9ac7_sm.jpg",
            "repImageUrl": "https://d2jf00asb0fe6y.cloudfront.net/california-gold-rush_07_5c95a64ae569a2071d1bdf5a308f9ac7_rep.jpg",
          "name": "California Gold Rush"
        },
        {
          "@id": "https://dp.la/primary-source-sets/sets/the-american-whaling-industry",
            "thumbnailUrl": "https://d2jf00asb0fe6y.cloudfront.net/american-whaling-industry_01_30071d8f8ed1b2a66f4bbb615f15eaf5_sm.jpg",
            "repImageUrl": "https://d2jf00asb0fe6y.cloudfront.net/american-whaling-industry_01_30071d8f8ed1b2a66f4bbb615f15eaf5_rep.jpg",
          "name": "The American Whaling Industry"
        },
        {
          "@id": "https://dp.la/primary-source-sets/sets/the-panic-of-1837",
            "thumbnailUrl": "https://d2jf00asb0fe6y.cloudfront.net/panic-1837_02_352b22c62314cc50a42f1a42e40d9920_sm.jpg",
            "repImageUrl": "https://d2jf00asb0fe6y.cloudfront.net/panic-1837_02_352b22c62314cc50a42f1a42e40d9920_rep.jpg",
          "name": "The Panic of 1837"
        },
        {
          "@id": "https://dp.la/primary-source-sets/sets/mormon-migration",
            "thumbnailUrl": "https://d2jf00asb0fe6y.cloudfront.net/mormon-migration_08_7102c301d9f3a440ba1ba0eae23afcb3_sm.jpg",
            "repImageUrl": "https://d2jf00asb0fe6y.cloudfront.net/mormon-migration_08_7102c301d9f3a440ba1ba0eae23afcb3_rep.jpg",
          "name": "Mormon Migration"
        },
        {
          "@id": "https://dp.la/primary-source-sets/sets/the-columbian-exchange",
            "thumbnailUrl": "https://d2jf00asb0fe6y.cloudfront.net/columbian-exchange_13_f587acd2680838b85166d18e086dbd93_sm.jpg",
            "repImageUrl": "https://d2jf00asb0fe6y.cloudfront.net/columbian-exchange_13_f587acd2680838b85166d18e086dbd93_rep.jpg",
          "name": "The Columbian Exchange"
        },
        {
          "@id": "https://dp.la/primary-source-sets/sets/cherokee-removal-and-the-trail-of-tears",
            "thumbnailUrl": "https://d2jf00asb0fe6y.cloudfront.net/cherokee-removal_01_35b35b794c8f639d385d80e2033ee9a3_sm.jpg",
            "repImageUrl": "https://d2jf00asb0fe6y.cloudfront.net/cherokee-removal_01_35b35b794c8f639d385d80e2033ee9a3_rep.jpg",
          "name": "Cherokee Removal and the Trail of Tears"
        },
        {
          "@id": "https://dp.la/primary-source-sets/sets/nineteenth-century-schools-for-the-deaf-and-blind",
            "thumbnailUrl": "https://d2jf00asb0fe6y.cloudfront.net/nineteenth-century-schools_13_a62588352f03b54598df02429a6d76f5_sm.jpg",
            "repImageUrl": "https://d2jf00asb0fe6y.cloudfront.net/nineteenth-century-schools_13_a62588352f03b54598df02429a6d76f5_rep.jpg",
          "name": "Nineteenth-Century Schools for the Deaf and Blind"
        },
        {
          "@id": "https://dp.la/primary-source-sets/sets/spanish-missions-in-california",
            "thumbnailUrl": "https://d2jf00asb0fe6y.cloudfront.net/spanish-missions-california_08_058746342900ae4b3ceb3280c2bcbac0_sm.jpg",
            "repImageUrl": "https://d2jf00asb0fe6y.cloudfront.net/spanish-missions-california_08_058746342900ae4b3ceb3280c2bcbac0_rep.jpg",
          "name": "Spanish Missions in California"
        },
        {
          "@id": "https://dp.la/primary-source-sets/sets/treaty-of-versailles-and-the-end-of-world-war-i",
            "thumbnailUrl": "https://d2jf00asb0fe6y.cloudfront.net/treaty-versailles_06_4c448d4d0ef6a95fbf6fd460ba295aec_sm.jpg",
            "repImageUrl": "https://d2jf00asb0fe6y.cloudfront.net/treaty-versailles_06_4c448d4d0ef6a95fbf6fd460ba295aec_rep.jpg",
          "name": "Treaty of Versailles and the End of World War I"
        },
        {
          "@id": "https://dp.la/primary-source-sets/sets/full-steam-ahead-the-steam-engine-and-transportation-in-the-nineteenth-century",
            "thumbnailUrl": "https://d2jf00asb0fe6y.cloudfront.net/full-steam-ahead-steam-engine-transportation-nineteenth-century_12_5e43229ea7fbd766be94f30d0ac6e844_sm.jpg",
            "repImageUrl": "https://d2jf00asb0fe6y.cloudfront.net/full-steam-ahead-steam-engine-transportation-nineteenth-century_12_5e43229ea7fbd766be94f30d0ac6e844_rep.jpg",
          "name": "Full Steam Ahead: The Steam Engine and Transportation in the Nineteenth Century"
        },
        {
          "@id": "https://dp.la/primary-source-sets/sets/women-of-the-antebellum-reform-movement",
            "thumbnailUrl": "https://d2jf00asb0fe6y.cloudfront.net/women-antebellum-reform-movement_10a_a6ce8f23167d6512215adef9b3f0dcd5_sm.jpg",
            "repImageUrl": "https://d2jf00asb0fe6y.cloudfront.net/women-antebellum-reform-movement_10a_a6ce8f23167d6512215adef9b3f0dcd5_rep.jpg",
          "name": "Women of the Antebellum Reform Movement"
        },
        {
          "@id": "https://dp.la/primary-source-sets/sets/exploration-of-the-americas",
            "thumbnailUrl": "https://d2jf00asb0fe6y.cloudfront.net/exploration-of-the-americas_03a_053e2477d310990f0617fcb154c112c5_sm.jpg",
            "repImageUrl": "https://d2jf00asb0fe6y.cloudfront.net/exploration-of-the-americas_03a_053e2477d310990f0617fcb154c112c5_rep.jpg",
          "name": "Exploration of the Americas"
        },
        {
          "@id": "https://dp.la/primary-source-sets/sets/attacks-on-american-soil-pearl-harbor-and-september-11",
            "thumbnailUrl": "https://d2jf00asb0fe6y.cloudfront.net/attacks-american-soil-pearl-harbor-september-11_13a_624c119f80cb9de5df65136922aadd43_sm.jpg",
            "repImageUrl": "https://d2jf00asb0fe6y.cloudfront.net/attacks-american-soil-pearl-harbor-september-11_13a_624c119f80cb9de5df65136922aadd43_rep.jpg",
          "name": "Attacks on American Soil: Pearl Harbor and September 11"
        },
        {
          "@id": "https://dp.la/primary-source-sets/sets/the-war-of-1812",
            "thumbnailUrl": "https://d2jf00asb0fe6y.cloudfront.net/war-of-1812_06_583c0b101b9d669db262b7f9cdef8f8d_sm.jpg",
            "repImageUrl": "https://d2jf00asb0fe6y.cloudfront.net/war-of-1812_06_583c0b101b9d669db262b7f9cdef8f8d_rep.jpg",
          "name": "The War of 1812"
        },
        {
          "@id": "https://dp.la/primary-source-sets/sets/manifest-destiny",
            "thumbnailUrl": "https://d2jf00asb0fe6y.cloudfront.net/manifest-destiny_04_e606ebe2044769b88a5ad7ccb661adc2_sm.jpg",
            "repImageUrl": "https://d2jf00asb0fe6y.cloudfront.net/manifest-destiny_04_e606ebe2044769b88a5ad7ccb661adc2_rep.jpg",
          "name": "Manifest Destiny"
        },
        {
          "@id": "https://dp.la/primary-source-sets/sets/henry-clay-the-great-compromiser",
            "thumbnailUrl": "https://d2jf00asb0fe6y.cloudfront.net/henry-clay-great-compromiser_07_8caba62b34f3acfb24f7a49c85656d0e_sm.jpg",
            "repImageUrl": "https://d2jf00asb0fe6y.cloudfront.net/henry-clay-great-compromiser_07_8caba62b34f3acfb24f7a49c85656d0e_rep.jpg",
          "name": "Henry Clay: The Great Compromiser"
        },
        {
          "@id": "https://dp.la/primary-source-sets/sets/the-lewis-and-clark-expedition",
            "thumbnailUrl": "https://d2jf00asb0fe6y.cloudfront.net/lewis-and-clark_00_77108df4a0ce1448e69116a5d6ac8d40.jpg",
            "repImageUrl": "https://d2jf00asb0fe6y.cloudfront.net/lewis-and-clark_00_77108df4a0ce1448e69116a5d6ac8d40_rep.jpg",
          "name": "The Lewis and Clark Expedition"
        },
        {
          "@id": "https://dp.la/primary-source-sets/sets/the-american-abolitionist-movement",
            "thumbnailUrl": "https://d2jf00asb0fe6y.cloudfront.net/abolition-movement_00_821567a4509c13c237dc63f2eb7fdb92.jpg",
            "repImageUrl": "https://d2jf00asb0fe6y.cloudfront.net/abolition-movement_00_821567a4509c13c237dc63f2eb7fdb92_rep.jpg",
          "name": "The American Abolitionist Movement"
        },
        {
          "@id": "https://dp.la/primary-source-sets/sets/the-transatlantic-slave-trade",
            "thumbnailUrl": "https://d2jf00asb0fe6y.cloudfront.net/transatlantic-slave-trade_00_bef1458b2e0f2b0fe1d657fef0e1f40a.jpg",
            "repImageUrl": "https://d2jf00asb0fe6y.cloudfront.net/transatlantic-slave-trade_00_bef1458b2e0f2b0fe1d657fef0e1f40a_rep.jpg",
          "name": "The Transatlantic Slave Trade"
        },
        {
          "@id": "https://dp.la/primary-source-sets/sets/the-panama-canal",
            "thumbnailUrl": "https://d2jf00asb0fe6y.cloudfront.net/panama-canal_00_52019b6dc4e90a6a20ffd40ad7920bef.jpg",
            "repImageUrl": "https://d2jf00asb0fe6y.cloudfront.net/panama-canal_00_52019b6dc4e90a6a20ffd40ad7920bef_rep.jpg",
          "name": "The Panama Canal"
        },
        {
          "@id": "https://dp.la/primary-source-sets/sets/jacksonian-democracy",
            "thumbnailUrl": "https://d2jf00asb0fe6y.cloudfront.net/jacksonian-democracy_00_6ec5f86f585a556cb557ec25a3d7c755.jpg",
            "repImageUrl": "https://d2jf00asb0fe6y.cloudfront.net/jacksonian-democracy_00_6ec5f86f585a556cb557ec25a3d7c755_rep.jpg",
          "name": "Jacksonian Democracy?"
        }
    ],
  "inLanguage": [
    {
      "@id": "http://lexvo.org/id/term/eng/English",
      "@type": "Language",
      "name": "English"
    }
  ],
  "learningResourceType": "Source Set",
  "license": "http://dp.la/info/terms/",
  "typicalAgeRange": "11-18",
  "accessbilityFeature": [
    "captions",
    "structuralNavigation",
    "audioControl",
    "videoControl"
  ],
  "accessibilityHazard": [
    "noFlashingHazard",
    "motionSimulation",
    "noSoundHazard"
  ],
  "accessibilityControl": [
    "fullMouseControl"
  ],
  "educationalAlignment": [
    {
      "@type": "AlignmentObject",
      "alignmentType": "requires",
      "educationalFramework": "Common Core State Standards",
      "targetName": "CCSS.ELA-Literacy.RH.6-8.7",
      "targetUrl": "ccss:ELA-Literacy/RH/6-8/7/"
    },
    {
      "@type": "AlignmentObject",
      "alignmentType": "requires",
      "educationalFramework": "Common Core State Standards",
      "targetName": "CCSS.ELA-Literacy.RH.6-8.7",
      "targetUrl": "ccss:ELA-Literacy/RH/6-8/7/"
    },
    {
      "@type": "AlignmentObject",
      "alignmentType": "requires",
      "educationalFramework": "Common Core State Standards",
      "targetName": "CCSS.ELA-Literacy.RH.6-8.9",
      "targetUrl": "ccss:ELA-Literacy/RH/6-8/9/"
    },
    {
      "@type": "AlignmentObject",
      "alignmentType": "requires",
      "educationalFramework": "Common Core State Standards",
      "targetName": "CCSS.ELA-Literacy.RH.9-10.9",
      "targetUrl": "ccss:ELA-Literacy/RH/9-10/9/"
    },
    {
      "@type": "AlignmentObject",
      "alignmentType": "requires",
      "educationalFramework": "Common Core State Standards",
      "targetName": "CCSS.ELA-Literacy.RH.11-12.7",
      "targetUrl": "ccss:ELA-Literacy/RH/11-12/7/"
    },
    {
      "@type": "AlignmentObject",
      "alignmentType": "requires",
      "educationalFramework": "Common Core State Standards",
      "targetName": "CCSS.ELA-Literacy.RH.11-12.9",
      "targetUrl": "ccss:ELA-Literacy/RH/11-12/9/"
    },
    {
      "@type": "AlignmentObject",
      "alignmentType": "requires",
      "educationalFramework": "Common Core State Standards",
      "targetName": "CCSS.ELA-Literacy.CCRA.R.7",
      "targetUrl": "ccss:ELA-Literacy/CCRA/R/7/"
    },
    {
      "@type": "AlignmentObject",
      "alignmentType": "requires",
      "educationalFramework": "Common Core State Standards",
      "targetName": "CCSS.ELA-Literacy.CCRA.W.8",
      "targetUrl": "ccss:ELA-Literacy/CCRA/W/8/"
    },
    {
      "@type": "AlignmentObject",
      "alignmentType": "requires",
      "educationalFramework": "Common Core State Standards",
      "targetName": "CCSS.ELA-Literacy.WHST.6-8.8",
      "targetUrl": "ccss:ELA-Literacy/WHST/6-8/8/"
    },
    {
      "@type": "AlignmentObject",
      "alignmentType": "requires",
      "educationalFramework": "Common Core State Standards",
      "targetName": "CCSS.ELA-Literacy.WHST.9-10.8",
      "targetUrl": "ccss:ELA-Literacy/WHST/9-10/8/"
    },
    {
      "@type": "AlignmentObject",
      "alignmentType": "requires",
      "educationalFramework": "Common Core State Standards",
      "targetName": "CCSS.ELA-Literacy.WHST.11-12.8",
      "targetUrl": "ccss:ELA-Literacy/WHST/11-12/8/"
    }
  ]
}
